{"items":[{"title":"がっこうのおばけずかん　ワンデイてんこうせい","displayTitle":"がっこうのおばけずかん　ワンデイてんこうせい","author":"斉藤 洋/宮本 えつよし","publisher":"講談社","genre":"小説","genreId":"001003002006/001003001001/001004008003","imageUrl":"https://thumbnail.image.rakuten.co.jp/@0_mall/book/cabinet/6014/9784061996014_1_3.jpg?_ex=800x800","hasRealCover":true,"isbn":"9784061996014","itemUrl":"https://books.rakuten.co.jp/rb/12759215/","price":1210,"firstReleaseDate":"2014年06月20日頃","label":"どうわがいっぱい","seriesName":"どうわがいっぱい","volumeCount":1,"coverCandidates":[{"imageUrl":"https://thumbnail.image.rakuten.co.jp/@0_mall/book/cabinet/6014/9784061996014_1_3.jpg?_ex=800x800","isbn":"9784061996014","hasRealCover":true}]},{"title":"海賊とよばれた男（下）","displayTitle":"海賊とよばれた男（下）","author":"百田 尚樹","publisher":"講談社","genre":"小説","genreId":"001019001/001004008006","imageUrl":"https://thumbnail.image.rakuten.co.jp/@0_mall/book/cabinet/8305/9784062778305_1_9.jpg?_ex=800x800","hasRealCover":true,"isbn":"9784062778305","itemUrl":"https://books.rakuten.co.jp/rb/12800594/","price":957,"firstReleaseDate":"2014年07月15日頃","label":"講談社文庫","seriesName":"講談社文庫","volumeCount":1,"coverCandidates":[{"imageUrl":"https://thumbnail.image.rakuten.co.jp/@0_mall/book/cabinet/8305/9784062778305_1_9.jpg?_ex=800x800","isbn":"9784062778305","hasRealCover":true}]},{"title":"10分間の官能小説集3","displayTitle":"10分間の官能小説集3","author":"小説現代/内藤 みか/南 綾子/小手鞠 るい/乾 くるみ/草凪 優","publisher":"講談社","genre":"小説","genreId":"001019001/001004008005/001004008003","imageUrl":"https://thumbnail.image.rakuten.co.jp/@0_mall/book/cabinet/8985/9784062778985.jpg?_ex=800x800","hasRealCover":true,"isbn":"9784062778985","itemUrl":"https://books.rakuten.co.jp/rb/12835301/","price":682,"firstReleaseDate":"2014年09月12日頃","label":"講談社文庫","seriesName":"講談社文庫","volumeCount":1,"coverCandidates":[{"imageUrl":"https://thumbnail.image.rakuten.co.jp/@0_mall/book/cabinet/8985/9784062778985.jpg?_ex=800x800","isbn":"9784062778985","hasRealCover":true}]},{"title":"探偵チームKZ事件ノート　赤い仮面は知っている","displayTitle":"探偵チームKZ事件ノート　赤い仮面は知っている","author":"住滝 良/藤本 ひとみ/駒形","publisher":"講談社","genre":"小説","genreId":"001020004/001003002002/001003001001/001004008003","imageUrl":"https://thumbnail.image.rakuten.co.jp/@0_mall/book/cabinet/4627/9784062854627.jpg?_ex=800x800","hasRealCover":true,"isbn":"9784062854627","itemUrl":"https://books.rakuten.co.jp/rb/13053066/","price":814,"firstReleaseDate":"2014年12月12日頃","label":"講談社青い鳥文庫","seriesName":"講談社青い鳥文庫","volumeCount":1,"coverCandidates":[{"imageUrl":"https://thumbnail.image.rakuten.co.jp/@0_mall/book/cabinet/4627/9784062854627.jpg?_ex=800x800","isbn":"9784062854627","hasRealCover":true}]},{"title":"外天楼","displayTitle":"外天楼","author":"石黒 正数","publisher":"講談社","genre":"小説","genreId":"001019001/001004008001","imageUrl":"https://thumbnail.image.rakuten.co.jp/@0_mall/book/cabinet/0888/9784062930888_1_20.jpg?_ex=800x800","hasRealCover":true,"isbn":"9784062930888","itemUrl":"https://books.rakuten.co.jp/rb/13169413/","price":748,"firstReleaseDate":"2015年04月15日頃","label":"講談社文庫","seriesName":"講談社文庫","volumeCount":1,"coverCandidates":[{"imageUrl":"https://thumbnail.image.rakuten.co.jp/@0_mall/book/cabinet/0888/9784062930888_1_20.jpg?_ex=800x800","isbn":"9784062930888","hasRealCover":true}]},{"title":"妖精チームG事件ノート　星形クッキーは知っている","displayTitle":"妖精チームG事件ノート　星形クッキーは知っている","author":"住滝 良/藤本 ひとみ/清瀬 赤目","publisher":"講談社","genre":"小説","genreId":"001020004/001003002002/001003001001/001004008003","imageUrl":"https://thumbnail.image.rakuten.co.jp/@0_mall/book/cabinet/4917/9784062854917.jpg?_ex=800x800","hasRealCover":true,"isbn":"9784062854917","itemUrl":"https://books.rakuten.co.jp/rb/13187347/","price":814,"firstReleaseDate":"2015年05月13日頃","label":"講談社青い鳥文庫","seriesName":"講談社青い鳥文庫","volumeCount":1,"coverCandidates":[{"imageUrl":"https://thumbnail.image.rakuten.co.jp/@0_mall/book/cabinet/4917/9784062854917.jpg?_ex=800x800","isbn":"9784062854917","hasRealCover":true}]},{"title":"がっこうのおばけずかん　おばけにゅうがくしき","displayTitle":"がっこうのおばけずかん　おばけにゅうがくしき","author":"斉藤 洋/宮本 えつよし","publisher":"講談社","genre":"小説","genreId":"001003002006/001003001001/001004008003","imageUrl":"https://thumbnail.image.rakuten.co.jp/@0_mall/book/cabinet/6052/9784061996052.jpg?_ex=800x800","hasRealCover":true,"isbn":"9784061996052","itemUrl":"https://books.rakuten.co.jp/rb/13291590/","price":1210,"firstReleaseDate":"2015年08月26日頃","label":"どうわがいっぱい","seriesName":"どうわがいっぱい","volumeCount":1,"coverCandidates":[{"imageUrl":"https://thumbnail.image.rakuten.co.jp/@0_mall/book/cabinet/6052/9784061996052.jpg?_ex=800x800","isbn":"9784061996052","hasRealCover":true}]},{"title":"さきちゃんたちの夜","displayTitle":"さきちゃんたちの夜","author":"よしもと ばなな","publisher":"新潮社","genre":"小説","genreId":"001019001/001004015/001004008008","imageUrl":"https://thumbnail.image.rakuten.co.jp/@0_mall/book/cabinet/9441/9784101359441.jpg?_ex=800x800","hasRealCover":true,"isbn":"9784101359441","itemUrl":"https://books.rakuten.co.jp/rb/13340896/","price":572,"firstReleaseDate":"2015年08月28日頃","label":"新潮文庫","seriesName":"新潮文庫","volumeCount":1,"coverCandidates":[{"imageUrl":"https://thumbnail.image.rakuten.co.jp/@0_mall/book/cabinet/9441/9784101359441.jpg?_ex=800x800","isbn":"9784101359441","hasRealCover":true}]},{"title":"ブラックライダー（下）","displayTitle":"ブラックライダー（下）","author":"東山 彰良","publisher":"新潮社","genre":"小説","genreId":"001019001/001004008006","imageUrl":"https://thumbnail.image.rakuten.co.jp/@0_mall/book/cabinet/1528/9784101201528.jpg?_ex=800x800","hasRealCover":true,"isbn":"9784101201528","itemUrl":"https://books.rakuten.co.jp/rb/13429342/","price":825,"firstReleaseDate":"2015年10月28日頃","label":"新潮文庫","seriesName":"新潮文庫","volumeCount":1,"coverCandidates":[{"imageUrl":"https://thumbnail.image.rakuten.co.jp/@0_mall/book/cabinet/1528/9784101201528.jpg?_ex=800x800","isbn":"9784101201528","hasRealCover":true}]},{"title":"ブラックライダー（上）","displayTitle":"ブラックライダー（上）","author":"東山 彰良","publisher":"新潮社","genre":"小説","genreId":"001019001/001004008006","imageUrl":"https://thumbnail.image.rakuten.co.jp/@0_mall/book/cabinet/1511/9784101201511.jpg?_ex=800x800","hasRealCover":true,"isbn":"9784101201511","itemUrl":"https://books.rakuten.co.jp/rb/13429341/","price":737,"firstReleaseDate":"2015年10月28日頃","label":"新潮文庫","seriesName":"新潮文庫","volumeCount":1,"coverCandidates":[{"imageUrl":"https://thumbnail.image.rakuten.co.jp/@0_mall/book/cabinet/1511/9784101201511.jpg?_ex=800x800","isbn":"9784101201511","hasRealCover":true}]},{"title":"空白を満たしなさい（下）","displayTitle":"空白を満たしなさい（下）","author":"平野 啓一郎","publisher":"講談社","genre":"小説","genreId":"001019001/001004008006","imageUrl":"https://thumbnail.image.rakuten.co.jp/@0_mall/book/cabinet/2899/9784062932899.jpg?_ex=800x800","hasRealCover":true,"isbn":"9784062932899","itemUrl":"https://books.rakuten.co.jp/rb/13441570/","price":814,"firstReleaseDate":"2015年11月13日頃","label":"講談社文庫","seriesName":"講談社文庫","volumeCount":1,"coverCandidates":[{"imageUrl":"https://thumbnail.image.rakuten.co.jp/@0_mall/book/cabinet/2899/9784062932899.jpg?_ex=800x800","isbn":"9784062932899","hasRealCover":true}]},{"title":"もし高校野球の女子マネージャーがドラッカーの『マネジメント』を読んだら","displayTitle":"もし高校野球の女子マネージャーがドラッカーの『マネジメント』を読んだら","author":"岩崎 夏海","publisher":"新潮社","genre":"小説","genreId":"001019008/001019001/001004008001/001004004003","imageUrl":"https://thumbnail.image.rakuten.co.jp/@0_mall/book/cabinet/2211/9784101202211.jpg?_ex=800x800","hasRealCover":true,"isbn":"9784101202211","itemUrl":"https://books.rakuten.co.jp/rb/13465440/","price":693,"firstReleaseDate":"2015年11月28日頃","label":"新潮文庫","seriesName":"新潮文庫","volumeCount":1,"coverCandidates":[{"imageUrl":"https://thumbnail.image.rakuten.co.jp/@0_mall/book/cabinet/2211/9784101202211.jpg?_ex=800x800","isbn":"9784101202211","hasRealCover":true}]},{"title":"改訂完全版　斜め屋敷の犯罪","displayTitle":"改訂完全版　斜め屋敷の犯罪","author":"島田 荘司","publisher":"講談社","genre":"小説","genreId":"001019001/001004008003","imageUrl":"https://thumbnail.image.rakuten.co.jp/@0_mall/book/cabinet/2653/9784062932653.jpg?_ex=800x800","hasRealCover":true,"isbn":"9784062932653","itemUrl":"https://books.rakuten.co.jp/rb/13516041/","price":924,"firstReleaseDate":"2016年01月15日頃","label":"講談社文庫","seriesName":"講談社文庫","volumeCount":1,"coverCandidates":[{"imageUrl":"https://thumbnail.image.rakuten.co.jp/@0_mall/book/cabinet/2653/9784062932653.jpg?_ex=800x800","isbn":"9784062932653","hasRealCover":true}]},{"title":"村上海賊の娘（三）","displayTitle":"村上海賊の娘（三）","author":"和田 竜","publisher":"新潮社","genre":"小説","genreId":"001019001/001004008008","imageUrl":"https://thumbnail.image.rakuten.co.jp/@0_mall/book/cabinet/9800/9784101349800.jpg?_ex=800x800","hasRealCover":true,"isbn":"9784101349800","itemUrl":"https://books.rakuten.co.jp/rb/14280228/","price":825,"firstReleaseDate":"2016年07月28日頃","label":"新潮文庫","seriesName":"新潮文庫","volumeCount":1,"coverCandidates":[{"imageUrl":"https://thumbnail.image.rakuten.co.jp/@0_mall/book/cabinet/9800/9784101349800.jpg?_ex=800x800","isbn":"9784101349800","hasRealCover":true}]},{"title":"夫婦善哉 決定版","displayTitle":"夫婦善哉 決定版","author":"織田 作之助","publisher":"新潮社","genre":"小説","genreId":"001019015/001019001/001004008001","imageUrl":"https://thumbnail.image.rakuten.co.jp/@0_mall/book/cabinet/7028/9784101037028.jpg?_ex=800x800","hasRealCover":true,"isbn":"9784101037028","itemUrl":"https://books.rakuten.co.jp/rb/14343424/","price":649,"firstReleaseDate":"2016年08月27日頃","label":"新潮文庫","seriesName":"新潮文庫","volumeCount":1,"coverCandidates":[{"imageUrl":"https://thumbnail.image.rakuten.co.jp/@0_mall/book/cabinet/7028/9784101037028.jpg?_ex=800x800","isbn":"9784101037028","hasRealCover":true}]},{"title":"怪人二十面相","displayTitle":"怪人二十面相","author":"江戸川 乱歩","publisher":"新潮社","genre":"小説","genreId":"001019001/001004008001","imageUrl":"https://thumbnail.image.rakuten.co.jp/@0_mall/book/cabinet/0783/9784101800783.jpg?_ex=800x800","hasRealCover":true,"isbn":"9784101800783","itemUrl":"https://books.rakuten.co.jp/rb/14392439/","price":605,"firstReleaseDate":"2016年09月28日頃","label":"新潮文庫","seriesName":"新潮文庫","volumeCount":1,"coverCandidates":[{"imageUrl":"https://thumbnail.image.rakuten.co.jp/@0_mall/book/cabinet/0783/9784101800783.jpg?_ex=800x800","isbn":"9784101800783","hasRealCover":true}]},{"title":"五年前の忘れ物","displayTitle":"五年前の忘れ物","author":"益田 ミリ","publisher":"講談社","genre":"小説","genreId":"001019001/001004008007","imageUrl":"https://thumbnail.image.rakuten.co.jp/@0_mall/book/cabinet/4916/9784062934916_1_15.jpg?_ex=800x800","hasRealCover":true,"isbn":"9784062934916","itemUrl":"https://books.rakuten.co.jp/rb/14398429/","price":726,"firstReleaseDate":"2016年09月15日頃","label":"講談社文庫","seriesName":"講談社文庫","volumeCount":1,"coverCandidates":[{"imageUrl":"https://thumbnail.image.rakuten.co.jp/@0_mall/book/cabinet/4916/9784062934916_1_15.jpg?_ex=800x800","isbn":"9784062934916","hasRealCover":true}]},{"title":"首折り男のための協奏曲","displayTitle":"首折り男のための協奏曲","author":"伊坂 幸太郎","publisher":"新潮社","genre":"小説","genreId":"001019001/001004015/001004008001","imageUrl":"https://thumbnail.image.rakuten.co.jp/@0_mall/book/cabinet/0311/9784101250311.jpg?_ex=800x800","hasRealCover":true,"isbn":"9784101250311","itemUrl":"https://books.rakuten.co.jp/rb/14537272/","price":880,"firstReleaseDate":"2016年11月29日頃","label":"新潮文庫","seriesName":"新潮文庫","volumeCount":1,"coverCandidates":[{"imageUrl":"https://thumbnail.image.rakuten.co.jp/@0_mall/book/cabinet/0311/9784101250311.jpg?_ex=800x800","isbn":"9784101250311","hasRealCover":true}]},{"title":"X’mas Stories","displayTitle":"X’mas Stories","author":"朝井 リョウ/あさの あつこ/伊坂 幸太郎/恩田 陸/白河 三兎/三浦 しをん","publisher":"新潮社","genre":"小説","genreId":"001019001/001004015/001004008001","imageUrl":"https://thumbnail.image.rakuten.co.jp/@0_mall/book/cabinet/2567/9784101332567_1_2.jpg?_ex=800x800","hasRealCover":true,"isbn":"9784101332567","itemUrl":"https://books.rakuten.co.jp/rb/14537307/","price":693,"firstReleaseDate":"2016年11月14日頃","label":"新潮文庫","seriesName":"新潮文庫","volumeCount":1,"coverCandidates":[{"imageUrl":"https://thumbnail.image.rakuten.co.jp/@0_mall/book/cabinet/2567/9784101332567_1_2.jpg?_ex=800x800","isbn":"9784101332567","hasRealCover":true}]},{"title":"吾輩も猫である","displayTitle":"吾輩も猫である","author":"赤川 次郎/新井 素子/石田 衣良/荻原 浩/恩田 陸/原田 マハ","publisher":"新潮社","genre":"小説","genreId":"001019001/001004015/001004008001","imageUrl":"https://thumbnail.image.rakuten.co.jp/@0_mall/book/cabinet/0502/9784101010502.jpg?_ex=800x800","hasRealCover":true,"isbn":"9784101010502","itemUrl":"https://books.rakuten.co.jp/rb/14537201/","price":605,"firstReleaseDate":"2016年11月29日頃","label":"新潮文庫","seriesName":"新潮文庫","volumeCount":1,"coverCandidates":[{"imageUrl":"https://thumbnail.image.rakuten.co.jp/@0_mall/book/cabinet/0502/9784101010502.jpg?_ex=800x800","isbn":"9784101010502","hasRealCover":true}]},{"title":"双孔堂の殺人　〜Double　Torus〜","displayTitle":"双孔堂の殺人　〜Double　Torus〜","author":"周木 律","publisher":"講談社","genre":"小説","genreId":"001019001/001004008003","imageUrl":"https://thumbnail.image.rakuten.co.jp/@0_mall/book/cabinet/5487/9784062935487_1_11.jpg?_ex=800x800","hasRealCover":true,"isbn":"9784062935487","itemUrl":"https://books.rakuten.co.jp/rb/14559114/","price":968,"firstReleaseDate":"2016年12月15日頃","label":"講談社文庫","seriesName":"講談社文庫","volumeCount":1,"coverCandidates":[{"imageUrl":"https://thumbnail.image.rakuten.co.jp/@0_mall/book/cabinet/5487/9784062935487_1_11.jpg?_ex=800x800","isbn":"9784062935487","hasRealCover":true}]},{"title":"火花","displayTitle":"火花","author":"又吉 直樹","publisher":"文藝春秋","genre":"小説","genreId":"001019001/001004008007","imageUrl":"https://thumbnail.image.rakuten.co.jp/@0_mall/book/cabinet/7822/9784167907822_1_4.jpg?_ex=800x800","hasRealCover":true,"isbn":"9784167907822","itemUrl":"https://books.rakuten.co.jp/rb/14602267/","price":715,"firstReleaseDate":"2017年02月10日頃","label":"文春文庫","seriesName":"文春文庫","volumeCount":1,"coverCandidates":[{"imageUrl":"https://thumbnail.image.rakuten.co.jp/@0_mall/book/cabinet/7822/9784167907822_1_4.jpg?_ex=800x800","isbn":"9784167907822","hasRealCover":true}]},{"title":"どんどん橋、落ちた〈新装改訂版〉","displayTitle":"どんどん橋、落ちた〈新装改訂版〉","author":"綾辻 行人","publisher":"講談社","genre":"小説","genreId":"001019001/001004008001","imageUrl":"https://thumbnail.image.rakuten.co.jp/@0_mall/book/cabinet/5517/9784062935517_1_11.jpg?_ex=800x800","hasRealCover":true,"isbn":"9784062935517","itemUrl":"https://books.rakuten.co.jp/rb/14638257/","price":1023,"firstReleaseDate":"2017年02月15日頃","label":"講談社文庫","seriesName":"講談社文庫","volumeCount":1,"coverCandidates":[{"imageUrl":"https://thumbnail.image.rakuten.co.jp/@0_mall/book/cabinet/5517/9784062935517_1_11.jpg?_ex=800x800","isbn":"9784062935517","hasRealCover":true}]},{"title":"旅猫リポート","displayTitle":"旅猫リポート","author":"有川 浩","publisher":"講談社","genre":"小説","genreId":"001019001/001004008001","imageUrl":"https://thumbnail.image.rakuten.co.jp/@0_mall/book/cabinet/5616/9784062935616_1_23.jpg?_ex=800x800","hasRealCover":true,"isbn":"9784062935616","itemUrl":"https://books.rakuten.co.jp/rb/14638269/","price":770,"firstReleaseDate":"2017年02月15日頃","label":"講談社文庫","seriesName":"講談社文庫","volumeCount":1,"coverCandidates":[{"imageUrl":"https://thumbnail.image.rakuten.co.jp/@0_mall/book/cabinet/5616/9784062935616_1_23.jpg?_ex=800x800","isbn":"9784062935616","hasRealCover":true}]},{"title":"迷宮百年の睡魔　LABYRINTH　IN　ARM　OF　MORPHEUS","displayTitle":"迷宮百年の睡魔　LABYRINTH　IN　ARM　OF　MORPHEUS","author":"森 博嗣","publisher":"講談社","genre":"小説","genreId":"001019001/001004008007","imageUrl":"https://thumbnail.image.rakuten.co.jp/@0_mall/book/cabinet/6071/9784062936071.jpg?_ex=800x800","hasRealCover":true,"isbn":"9784062936071","itemUrl":"https://books.rakuten.co.jp/rb/14638278/","price":1078,"firstReleaseDate":"2017年02月15日頃","label":"講談社文庫","seriesName":"講談社文庫","volumeCount":1,"coverCandidates":[{"imageUrl":"https://thumbnail.image.rakuten.co.jp/@0_mall/book/cabinet/6071/9784062936071.jpg?_ex=800x800","isbn":"9784062936071","hasRealCover":true}]},{"title":"鬼平犯科帳 決定版（七）","displayTitle":"鬼平犯科帳 決定版（七）","author":"池波 正太郎","publisher":"文藝春秋","genre":"小説","genreId":"001019001/001004008001","imageUrl":"https://thumbnail.image.rakuten.co.jp/@0_mall/book/cabinet/8157/9784167908157_1_3.jpg?_ex=800x800","hasRealCover":true,"isbn":"9784167908157","itemUrl":"https://books.rakuten.co.jp/rb/14640864/","price":836,"firstReleaseDate":"2017年03月10日頃","label":"文春文庫","seriesName":"文春文庫","volumeCount":1,"coverCandidates":[{"imageUrl":"https://thumbnail.image.rakuten.co.jp/@0_mall/book/cabinet/8157/9784167908157_1_3.jpg?_ex=800x800","isbn":"9784167908157","hasRealCover":true}]},{"title":"鬼平犯科帳 決定版（九）","displayTitle":"鬼平犯科帳 決定版（九）","author":"池波 正太郎","publisher":"文藝春秋","genre":"小説","genreId":"001019001/001004008001","imageUrl":"https://thumbnail.image.rakuten.co.jp/@0_mall/book/cabinet/8379/9784167908379_1_5.jpg?_ex=800x800","hasRealCover":true,"isbn":"9784167908379","itemUrl":"https://books.rakuten.co.jp/rb/14677461/","price":847,"firstReleaseDate":"2017年04月07日頃","label":"文春文庫","seriesName":"文春文庫","volumeCount":1,"coverCandidates":[{"imageUrl":"https://thumbnail.image.rakuten.co.jp/@0_mall/book/cabinet/8379/9784167908379_1_5.jpg?_ex=800x800","isbn":"9784167908379","hasRealCover":true}]},{"title":"鬼平犯科帳 決定版（十）","displayTitle":"鬼平犯科帳 決定版（十）","author":"池波 正太郎","publisher":"文藝春秋","genre":"小説","genreId":"001019001/001004008001","imageUrl":"https://thumbnail.image.rakuten.co.jp/@0_mall/book/cabinet/8546/9784167908546_1_9.jpg?_ex=800x800","hasRealCover":true,"isbn":"9784167908546","itemUrl":"https://books.rakuten.co.jp/rb/14771391/","price":847,"firstReleaseDate":"2017年05月10日頃","label":"文春文庫","seriesName":"文春文庫","volumeCount":1,"coverCandidates":[{"imageUrl":"https://thumbnail.image.rakuten.co.jp/@0_mall/book/cabinet/8546/9784167908546_1_9.jpg?_ex=800x800","isbn":"9784167908546","hasRealCover":true}]},{"title":"西の魔女が死んだ 梨木香歩作品集","displayTitle":"西の魔女が死んだ 梨木香歩作品集","author":"梨木 香歩","publisher":"新潮社","genre":"日本の小説","genreId":"001004008005","imageUrl":"https://thumbnail.image.rakuten.co.jp/@0_mall/book/cabinet/9119/9784104299119.jpg?_ex=800x800","hasRealCover":true,"isbn":"9784104299119","itemUrl":"https://books.rakuten.co.jp/rb/14777328/","price":1870,"firstReleaseDate":"2017年04月27日頃","label":"","seriesName":"","volumeCount":1,"coverCandidates":[{"imageUrl":"https://thumbnail.image.rakuten.co.jp/@0_mall/book/cabinet/9119/9784104299119.jpg?_ex=800x800","isbn":"9784104299119","hasRealCover":true}]},{"title":"図書館の魔女　烏の伝言　（上）","displayTitle":"図書館の魔女　烏の伝言　（上）","author":"高田 大介","publisher":"講談社","genre":"小説","genreId":"001019001/001004008004","imageUrl":"https://thumbnail.image.rakuten.co.jp/@0_mall/book/cabinet/6538/9784062936538_1_16.jpg?_ex=800x800","hasRealCover":true,"isbn":"9784062936538","itemUrl":"https://books.rakuten.co.jp/rb/14837716/","price":858,"firstReleaseDate":"2017年05月16日頃","label":"講談社文庫","seriesName":"講談社文庫","volumeCount":1,"coverCandidates":[{"imageUrl":"https://thumbnail.image.rakuten.co.jp/@0_mall/book/cabinet/6538/9784062936538_1_16.jpg?_ex=800x800","isbn":"9784062936538","hasRealCover":true}]},{"title":"図書館の魔女　烏の伝言　（下）","displayTitle":"図書館の魔女　烏の伝言　（下）","author":"高田 大介","publisher":"講談社","genre":"小説","genreId":"001019001/001004008004","imageUrl":"https://thumbnail.image.rakuten.co.jp/@0_mall/book/cabinet/6545/9784062936545_1_17.jpg?_ex=800x800","hasRealCover":true,"isbn":"9784062936545","itemUrl":"https://books.rakuten.co.jp/rb/14837718/","price":858,"firstReleaseDate":"2017年05月16日頃","label":"講談社文庫","seriesName":"講談社文庫","volumeCount":1,"coverCandidates":[{"imageUrl":"https://thumbnail.image.rakuten.co.jp/@0_mall/book/cabinet/6545/9784062936545_1_17.jpg?_ex=800x800","isbn":"9784062936545","hasRealCover":true}]},{"title":"月光のスティグマ","displayTitle":"月光のスティグマ","author":"中山 七里","publisher":"新潮社","genre":"小説","genreId":"001019001/001004008005","imageUrl":"https://thumbnail.image.rakuten.co.jp/@0_mall/book/cabinet/9616/9784101209616.jpg?_ex=800x800","hasRealCover":true,"isbn":"9784101209616","itemUrl":"https://books.rakuten.co.jp/rb/14988335/","price":825,"firstReleaseDate":"2017年06月28日頃","label":"新潮文庫","seriesName":"新潮文庫","volumeCount":1,"coverCandidates":[{"imageUrl":"https://thumbnail.image.rakuten.co.jp/@0_mall/book/cabinet/9616/9784101209616.jpg?_ex=800x800","isbn":"9784101209616","hasRealCover":true}]},{"title":"Aではない君と","displayTitle":"Aではない君と","author":"薬丸 岳","publisher":"講談社","genre":"小説","genreId":"001019001/001004008008","imageUrl":"https://thumbnail.image.rakuten.co.jp/@0_mall/book/cabinet/7146/9784062937146_1_5.jpg?_ex=800x800","hasRealCover":true,"isbn":"9784062937146","itemUrl":"https://books.rakuten.co.jp/rb/15009086/","price":946,"firstReleaseDate":"2017年07月14日頃","label":"講談社文庫","seriesName":"講談社文庫","volumeCount":1,"coverCandidates":[{"imageUrl":"https://thumbnail.image.rakuten.co.jp/@0_mall/book/cabinet/7146/9784062937146_1_5.jpg?_ex=800x800","isbn":"9784062937146","hasRealCover":true}]},{"title":"波の音が消えるまで 第3部","displayTitle":"波の音が消えるまで 第3部","author":"沢木 耕太郎","publisher":"新潮社","genre":"小説","genreId":"001019001/001004008003","imageUrl":"https://thumbnail.image.rakuten.co.jp/@0_mall/book/cabinet/5257/9784101235257.jpg?_ex=800x800","hasRealCover":true,"isbn":"9784101235257","itemUrl":"https://books.rakuten.co.jp/rb/15031194/","price":693,"firstReleaseDate":"2017年07月28日頃","label":"新潮文庫","seriesName":"新潮文庫","volumeCount":1,"coverCandidates":[{"imageUrl":"https://thumbnail.image.rakuten.co.jp/@0_mall/book/cabinet/5257/9784101235257.jpg?_ex=800x800","isbn":"9784101235257","hasRealCover":true}]},{"title":"波の音が消えるまで 第2部","displayTitle":"波の音が消えるまで 第2部","author":"沢木 耕太郎","publisher":"新潮社","genre":"小説","genreId":"001019001/001004008003","imageUrl":"https://thumbnail.image.rakuten.co.jp/@0_mall/book/cabinet/5240/9784101235240.jpg?_ex=800x800","hasRealCover":true,"isbn":"9784101235240","itemUrl":"https://books.rakuten.co.jp/rb/15031195/","price":649,"firstReleaseDate":"2017年07月28日頃","label":"新潮文庫","seriesName":"新潮文庫","volumeCount":1,"coverCandidates":[{"imageUrl":"https://thumbnail.image.rakuten.co.jp/@0_mall/book/cabinet/5240/9784101235240.jpg?_ex=800x800","isbn":"9784101235240","hasRealCover":true}]},{"title":"満願","displayTitle":"満願","author":"米澤 穂信","publisher":"新潮社","genre":"小説","genreId":"001019001/001004008008","imageUrl":"https://thumbnail.image.rakuten.co.jp/@0_mall/book/cabinet/7843/9784101287843.jpg?_ex=800x800","hasRealCover":true,"isbn":"9784101287843","itemUrl":"https://books.rakuten.co.jp/rb/15031228/","price":825,"firstReleaseDate":"2017年07月28日頃","label":"新潮文庫","seriesName":"新潮文庫","volumeCount":1,"coverCandidates":[{"imageUrl":"https://thumbnail.image.rakuten.co.jp/@0_mall/book/cabinet/7843/9784101287843.jpg?_ex=800x800","isbn":"9784101287843","hasRealCover":true}]},{"title":"献灯使","displayTitle":"献灯使","author":"多和田 葉子","publisher":"講談社","genre":"小説","genreId":"001019001/001004008004","imageUrl":"https://thumbnail.image.rakuten.co.jp/@0_mall/book/cabinet/7283/9784062937283_1_7.jpg?_ex=800x800","hasRealCover":true,"isbn":"9784062937283","itemUrl":"https://books.rakuten.co.jp/rb/15044825/","price":715,"firstReleaseDate":"2017年08月08日頃","label":"講談社文庫","seriesName":"講談社文庫","volumeCount":1,"coverCandidates":[{"imageUrl":"https://thumbnail.image.rakuten.co.jp/@0_mall/book/cabinet/7283/9784062937283_1_7.jpg?_ex=800x800","isbn":"9784062937283","hasRealCover":true}]},{"title":"新装版　戦いすんで日が暮れて","displayTitle":"新装版　戦いすんで日が暮れて","author":"佐藤 愛子","publisher":"講談社","genre":"小説","genreId":"001019001/001004008003","imageUrl":"https://thumbnail.image.rakuten.co.jp/@0_mall/book/cabinet/7733/9784062937733_1_5.jpg?_ex=800x800","hasRealCover":true,"isbn":"9784062937733","itemUrl":"https://books.rakuten.co.jp/rb/15085396/","price":748,"firstReleaseDate":"2017年09月13日頃","label":"講談社文庫","seriesName":"講談社文庫","volumeCount":1,"coverCandidates":[{"imageUrl":"https://thumbnail.image.rakuten.co.jp/@0_mall/book/cabinet/7733/9784062937733_1_5.jpg?_ex=800x800","isbn":"9784062937733","hasRealCover":true}]},{"title":"ハゲタカ2．5　ハーディ（上）","displayTitle":"ハゲタカ2．5　ハーディ（上）","author":"真山 仁/山田 章博","publisher":"講談社","genre":"小説","genreId":"001019001/001004008008/001004008007","imageUrl":"https://thumbnail.image.rakuten.co.jp/@0_mall/book/cabinet/8075/9784062938075_1_7.jpg?_ex=800x800","hasRealCover":true,"isbn":"9784062938075","itemUrl":"https://books.rakuten.co.jp/rb/15201615/","price":704,"firstReleaseDate":"2017年11月15日頃","label":"講談社文庫","seriesName":"講談社文庫","volumeCount":1,"coverCandidates":[{"imageUrl":"https://thumbnail.image.rakuten.co.jp/@0_mall/book/cabinet/8075/9784062938075_1_7.jpg?_ex=800x800","isbn":"9784062938075","hasRealCover":true}]},{"title":"ハゲタカ2．5　ハーディ（下）","displayTitle":"ハゲタカ2．5　ハーディ（下）","author":"真山 仁/山田 章博","publisher":"講談社","genre":"小説","genreId":"001019001/001004008008/001004008007","imageUrl":"https://thumbnail.image.rakuten.co.jp/@0_mall/book/cabinet/8044/9784062938044_1_7.jpg?_ex=800x800","hasRealCover":true,"isbn":"9784062938044","itemUrl":"https://books.rakuten.co.jp/rb/15201618/","price":792,"firstReleaseDate":"2017年11月15日頃","label":"講談社文庫","seriesName":"講談社文庫","volumeCount":1,"coverCandidates":[{"imageUrl":"https://thumbnail.image.rakuten.co.jp/@0_mall/book/cabinet/8044/9784062938044_1_7.jpg?_ex=800x800","isbn":"9784062938044","hasRealCover":true}]},{"title":"天下 家康伝 下","displayTitle":"天下 家康伝 下","author":"火坂 雅志","publisher":"文藝春秋","genre":"小説","genreId":"001019001/001004008006","imageUrl":"https://thumbnail.image.rakuten.co.jp/@0_mall/book/cabinet/9956/9784167909956_1_3.jpg?_ex=800x800","hasRealCover":true,"isbn":"9784167909956","itemUrl":"https://books.rakuten.co.jp/rb/15231120/","price":946,"firstReleaseDate":"2018年01月04日頃","label":"文春文庫","seriesName":"文春文庫","volumeCount":1,"coverCandidates":[{"imageUrl":"https://thumbnail.image.rakuten.co.jp/@0_mall/book/cabinet/9956/9784167909956_1_3.jpg?_ex=800x800","isbn":"9784167909956","hasRealCover":true}]},{"title":"羊と鋼の森","displayTitle":"羊と鋼の森","author":"宮下 奈都","publisher":"文藝春秋","genre":"小説","genreId":"001019001/001004008007","imageUrl":"https://thumbnail.image.rakuten.co.jp/@0_mall/book/cabinet/0105/9784167910105_1_5.jpg?_ex=800x800","hasRealCover":true,"isbn":"9784167910105","itemUrl":"https://books.rakuten.co.jp/rb/15276073/","price":792,"firstReleaseDate":"2018年02月09日頃","label":"文春文庫","seriesName":"文春文庫","volumeCount":1,"coverCandidates":[{"imageUrl":"https://thumbnail.image.rakuten.co.jp/@0_mall/book/cabinet/0105/9784167910105_1_5.jpg?_ex=800x800","isbn":"9784167910105","hasRealCover":true}]},{"title":"その可能性はすでに考えた","displayTitle":"その可能性はすでに考えた","author":"井上 真偽","publisher":"講談社","genre":"小説","genreId":"001019001/001004008001","imageUrl":"https://thumbnail.image.rakuten.co.jp/@0_mall/book/cabinet/8532/9784062938532_1_17.jpg?_ex=800x800","hasRealCover":true,"isbn":"9784062938532","itemUrl":"https://books.rakuten.co.jp/rb/15315997/","price":858,"firstReleaseDate":"2018年02月15日頃","label":"講談社文庫","seriesName":"講談社文庫","volumeCount":1,"coverCandidates":[{"imageUrl":"https://thumbnail.image.rakuten.co.jp/@0_mall/book/cabinet/8532/9784062938532_1_17.jpg?_ex=800x800","isbn":"9784062938532","hasRealCover":true}]},{"title":"ある町の高い煙突","displayTitle":"ある町の高い煙突","author":"新田 次郎","publisher":"文藝春秋","genre":"小説","genreId":"001019001/001004008005","imageUrl":"https://thumbnail.image.rakuten.co.jp/@0_mall/book/cabinet/0365/9784167910365.jpg?_ex=800x800","hasRealCover":true,"isbn":"9784167910365","itemUrl":"https://books.rakuten.co.jp/rb/15318196/","price":825,"firstReleaseDate":"2018年03月09日頃","label":"文春文庫","seriesName":"文春文庫","volumeCount":1,"coverCandidates":[{"imageUrl":"https://thumbnail.image.rakuten.co.jp/@0_mall/book/cabinet/0365/9784167910365.jpg?_ex=800x800","isbn":"9784167910365","hasRealCover":true}]},{"title":"億男","displayTitle":"億男","author":"川村 元気","publisher":"文藝春秋","genre":"小説","genreId":"001019001/001004008002","imageUrl":"https://thumbnail.image.rakuten.co.jp/@0_mall/book/cabinet/0266/9784167910266.jpg?_ex=800x800","hasRealCover":true,"isbn":"9784167910266","itemUrl":"https://books.rakuten.co.jp/rb/15321840/","price":748,"firstReleaseDate":"2018年03月09日頃","label":"文春文庫","seriesName":"文春文庫","volumeCount":1,"coverCandidates":[{"imageUrl":"https://thumbnail.image.rakuten.co.jp/@0_mall/book/cabinet/0266/9784167910266.jpg?_ex=800x800","isbn":"9784167910266","hasRealCover":true}]},{"title":"さよなら、ニルヴァーナ","displayTitle":"さよなら、ニルヴァーナ","author":"窪 美澄","publisher":"文藝春秋","genre":"小説","genreId":"001019001/001004008002","imageUrl":"https://thumbnail.image.rakuten.co.jp/@0_mall/book/cabinet/0631/9784167910631_1_3.jpg?_ex=800x800","hasRealCover":true,"isbn":"9784167910631","itemUrl":"https://books.rakuten.co.jp/rb/15395522/","price":880,"firstReleaseDate":"2018年05月10日頃","label":"文春文庫","seriesName":"文春文庫","volumeCount":1,"coverCandidates":[{"imageUrl":"https://thumbnail.image.rakuten.co.jp/@0_mall/book/cabinet/0631/9784167910631_1_3.jpg?_ex=800x800","isbn":"9784167910631","hasRealCover":true}]},{"title":"小説　仮面ライダーエグゼイド　〜マイティノベルX〜","displayTitle":"小説　仮面ライダーエグゼイド　〜マイティノベルX〜","author":"東映/石ノ森 章太郎/高橋 悠也","publisher":"講談社","genre":"日本の小説","genreId":"001004008004/001004008001","imageUrl":"https://thumbnail.image.rakuten.co.jp/@0_mall/book/cabinet/8831/9784063148831_1_10.jpg?_ex=800x800","hasRealCover":true,"isbn":"9784063148831","itemUrl":"https://books.rakuten.co.jp/rb/15487434/","price":880,"firstReleaseDate":"2018年06月27日頃","label":"","seriesName":"","volumeCount":1,"coverCandidates":[{"imageUrl":"https://thumbnail.image.rakuten.co.jp/@0_mall/book/cabinet/8831/9784063148831_1_10.jpg?_ex=800x800","isbn":"9784063148831","hasRealCover":true}]},{"title":"聖女の毒杯　その可能性はすでに考えた","displayTitle":"聖女の毒杯　その可能性はすでに考えた","author":"井上 真偽","publisher":"講談社","genre":"小説","genreId":"001019001/001004008001","imageUrl":"https://thumbnail.image.rakuten.co.jp/@0_mall/book/cabinet/9433/9784065119433.jpg?_ex=800x800","hasRealCover":true,"isbn":"9784065119433","itemUrl":"https://books.rakuten.co.jp/rb/15517513/","price":902,"firstReleaseDate":"2018年07月13日頃","label":"講談社文庫","seriesName":"講談社文庫","volumeCount":1,"coverCandidates":[{"imageUrl":"https://thumbnail.image.rakuten.co.jp/@0_mall/book/cabinet/9433/9784065119433.jpg?_ex=800x800","isbn":"9784065119433","hasRealCover":true}]},{"title":"不連続殺人事件","displayTitle":"不連続殺人事件","author":"坂口 安吾","publisher":"新潮社","genre":"小説","genreId":"001019001/001004008003","imageUrl":"https://thumbnail.image.rakuten.co.jp/@0_mall/book/cabinet/4035/9784101024035.jpg?_ex=800x800","hasRealCover":true,"isbn":"9784101024035","itemUrl":"https://books.rakuten.co.jp/rb/15544563/","price":572,"firstReleaseDate":"2018年08月29日頃","label":"新潮文庫","seriesName":"新潮文庫","volumeCount":1,"coverCandidates":[{"imageUrl":"https://thumbnail.image.rakuten.co.jp/@0_mall/book/cabinet/4035/9784101024035.jpg?_ex=800x800","isbn":"9784101024035","hasRealCover":true}]},{"title":"冷血（下）","displayTitle":"冷血（下）","author":"高村 薫","publisher":"新潮社","genre":"小説","genreId":"001019001/001004008004","imageUrl":"https://thumbnail.image.rakuten.co.jp/@0_mall/book/cabinet/7264/9784101347264.jpg?_ex=800x800","hasRealCover":true,"isbn":"9784101347264","itemUrl":"https://books.rakuten.co.jp/rb/15626341/","price":825,"firstReleaseDate":"2018年10月27日頃","label":"新潮文庫","seriesName":"新潮文庫","volumeCount":1,"coverCandidates":[{"imageUrl":"https://thumbnail.image.rakuten.co.jp/@0_mall/book/cabinet/7264/9784101347264.jpg?_ex=800x800","isbn":"9784101347264","hasRealCover":true}]},{"title":"冷血（上）","displayTitle":"冷血（上）","author":"高村 薫","publisher":"新潮社","genre":"小説","genreId":"001019001/001004008004","imageUrl":"https://thumbnail.image.rakuten.co.jp/@0_mall/book/cabinet/7257/9784101347257.jpg?_ex=800x800","hasRealCover":true,"isbn":"9784101347257","itemUrl":"https://books.rakuten.co.jp/rb/15626340/","price":825,"firstReleaseDate":"2018年10月27日頃","label":"新潮文庫","seriesName":"新潮文庫","volumeCount":1,"coverCandidates":[{"imageUrl":"https://thumbnail.image.rakuten.co.jp/@0_mall/book/cabinet/7257/9784101347257.jpg?_ex=800x800","isbn":"9784101347257","hasRealCover":true}]},{"title":"希望荘","displayTitle":"希望荘","author":"宮部 みゆき","publisher":"文藝春秋","genre":"小説","genreId":"001019001/001004008007","imageUrl":"https://thumbnail.image.rakuten.co.jp/@0_mall/book/cabinet/1676/9784167911676_1_3.jpg?_ex=800x800","hasRealCover":true,"isbn":"9784167911676","itemUrl":"https://books.rakuten.co.jp/rb/15628665/","price":1012,"firstReleaseDate":"2018年11月09日頃","label":"文春文庫","seriesName":"文春文庫","volumeCount":1,"coverCandidates":[{"imageUrl":"https://thumbnail.image.rakuten.co.jp/@0_mall/book/cabinet/1676/9784167911676_1_3.jpg?_ex=800x800","isbn":"9784167911676","hasRealCover":true}]},{"title":"小説　ティガ・ダイナ＆ウルトラマンガイア　超時空のアドベンチャー","displayTitle":"小説　ティガ・ダイナ＆ウルトラマンガイア　超時空のアドベンチャー","author":"長谷川 圭一/円谷プロダクション","publisher":"講談社","genre":"日本の小説","genreId":"001004008006/001004008004","imageUrl":"https://thumbnail.image.rakuten.co.jp/@0_mall/book/cabinet/7611/9784065137611.jpg?_ex=800x800","hasRealCover":true,"isbn":"9784065137611","itemUrl":"https://books.rakuten.co.jp/rb/15657894/","price":748,"firstReleaseDate":"2018年12月02日頃","label":"","seriesName":"","volumeCount":1,"coverCandidates":[{"imageUrl":"https://thumbnail.image.rakuten.co.jp/@0_mall/book/cabinet/7611/9784065137611.jpg?_ex=800x800","isbn":"9784065137611","hasRealCover":true}]},{"title":"ボクたちはみんな大人になれなかった","displayTitle":"ボクたちはみんな大人になれなかった","author":"燃え殻","publisher":"新潮社","genre":"小説","genreId":"001019001/001004008007","imageUrl":"https://thumbnail.image.rakuten.co.jp/@0_mall/book/cabinet/3511/9784101003511.jpg?_ex=800x800","hasRealCover":true,"isbn":"9784101003511","itemUrl":"https://books.rakuten.co.jp/rb/15665828/","price":572,"firstReleaseDate":"2018年11月28日頃","label":"新潮文庫","seriesName":"新潮文庫","volumeCount":1,"coverCandidates":[{"imageUrl":"https://thumbnail.image.rakuten.co.jp/@0_mall/book/cabinet/3511/9784101003511.jpg?_ex=800x800","isbn":"9784101003511","hasRealCover":true}]},{"title":"この世にたやすい仕事はない","displayTitle":"この世にたやすい仕事はない","author":"津村 記久子","publisher":"新潮社","genre":"小説","genreId":"001019001/001004008004","imageUrl":"https://thumbnail.image.rakuten.co.jp/@0_mall/book/cabinet/1429/9784101201429.jpg?_ex=800x800","hasRealCover":true,"isbn":"9784101201429","itemUrl":"https://books.rakuten.co.jp/rb/15665832/","price":825,"firstReleaseDate":"2018年11月28日頃","label":"新潮文庫","seriesName":"新潮文庫","volumeCount":1,"coverCandidates":[{"imageUrl":"https://thumbnail.image.rakuten.co.jp/@0_mall/book/cabinet/1429/9784101201429.jpg?_ex=800x800","isbn":"9784101201429","hasRealCover":true}]},{"title":"100万分の1回のねこ","displayTitle":"100万分の1回のねこ","author":"江國 香織/岩瀬 成子/くどう なおこ/井上 荒野/角田 光代/町田 康","publisher":"講談社","genre":"小説","genreId":"001019001/001004008001","imageUrl":"https://thumbnail.image.rakuten.co.jp/@0_mall/book/cabinet/9981/9784065139981_1_11.jpg?_ex=800x800","hasRealCover":true,"isbn":"9784065139981","itemUrl":"https://books.rakuten.co.jp/rb/15722665/","price":737,"firstReleaseDate":"2018年12月14日頃","label":"講談社文庫","seriesName":"講談社文庫","volumeCount":1,"coverCandidates":[{"imageUrl":"https://thumbnail.image.rakuten.co.jp/@0_mall/book/cabinet/9981/9784065139981_1_11.jpg?_ex=800x800","isbn":"9784065139981","hasRealCover":true}]},{"title":"掟上今日子の推薦文","displayTitle":"掟上今日子の推薦文","author":"西尾 維新","publisher":"講談社","genre":"小説","genreId":"001019001/001004008005","imageUrl":"https://thumbnail.image.rakuten.co.jp/@0_mall/book/cabinet/3124/9784065143124.jpg?_ex=800x800","hasRealCover":true,"isbn":"9784065143124","itemUrl":"https://books.rakuten.co.jp/rb/15728346/","price":924,"firstReleaseDate":"2019年01月16日頃","label":"講談社文庫","seriesName":"講談社文庫","volumeCount":1,"coverCandidates":[{"imageUrl":"https://thumbnail.image.rakuten.co.jp/@0_mall/book/cabinet/3124/9784065143124.jpg?_ex=800x800","isbn":"9784065143124","hasRealCover":true}]},{"title":"浜村渚の計算ノート　9さつめ　恋人たちの必勝法","displayTitle":"浜村渚の計算ノート　9さつめ　恋人たちの必勝法","author":"青柳 碧人","publisher":"講談社","genre":"小説","genreId":"001019001/001004008001","imageUrl":"https://thumbnail.image.rakuten.co.jp/@0_mall/book/cabinet/5387/9784065155387_1_7.jpg?_ex=800x800","hasRealCover":true,"isbn":"9784065155387","itemUrl":"https://books.rakuten.co.jp/rb/15837490/","price":748,"firstReleaseDate":"2019年04月16日頃","label":"講談社文庫","seriesName":"講談社文庫","volumeCount":1,"coverCandidates":[{"imageUrl":"https://thumbnail.image.rakuten.co.jp/@0_mall/book/cabinet/5387/9784065155387_1_7.jpg?_ex=800x800","isbn":"9784065155387","hasRealCover":true}]},{"title":"武士の流儀（一）","displayTitle":"武士の流儀（一）","author":"稲葉 稔","publisher":"文藝春秋","genre":"小説","genreId":"001019001/001004008001","imageUrl":"https://thumbnail.image.rakuten.co.jp/@0_mall/book/cabinet/3014/9784167913014_1_3.jpg?_ex=800x800","hasRealCover":true,"isbn":"9784167913014","itemUrl":"https://books.rakuten.co.jp/rb/15879490/","price":825,"firstReleaseDate":"2019年06月06日頃","label":"文春文庫","seriesName":"文春文庫","volumeCount":1,"coverCandidates":[{"imageUrl":"https://thumbnail.image.rakuten.co.jp/@0_mall/book/cabinet/3014/9784167913014_1_3.jpg?_ex=800x800","isbn":"9784167913014","hasRealCover":true}]},{"title":"何様","displayTitle":"何様","author":"朝井 リョウ","publisher":"新潮社","genre":"小説","genreId":"001019001/001004008001","imageUrl":"https://thumbnail.image.rakuten.co.jp/@0_mall/book/cabinet/9320/9784101269320_1_3.jpg?_ex=800x800","hasRealCover":true,"isbn":"9784101269320","itemUrl":"https://books.rakuten.co.jp/rb/15905772/","price":825,"firstReleaseDate":"2019年06月26日頃","label":"新潮文庫","seriesName":"新潮文庫","volumeCount":1,"coverCandidates":[{"imageUrl":"https://thumbnail.image.rakuten.co.jp/@0_mall/book/cabinet/9320/9784101269320_1_3.jpg?_ex=800x800","isbn":"9784101269320","hasRealCover":true}]}],"page":7,"totalPages":25,"totalCount":1477,"itemsPerPage":60}